dgpy/__about__.py
dgpy/__init__.py
dgpy/__main__.py
dgpy/_self.py
dgpy/_types.py
dgpy/aio.py
dgpy/argskwargs.py
dgpy/bdat.py
dgpy/const.py
dgpy/core/__init__.py
dgpy/core/_cv.py
dgpy/core/_ev.py
dgpy/core/_exes.py
dgpy/core/_wa.py
dgpy/core/boundingbox.py
dgpy/core/config.py
dgpy/core/enums/__init__.py
dgpy/core/enums/eve.py
dgpy/core/enums/evp.py
dgpy/core/enums/evr.py
dgpy/core/enums/evt.py
dgpy/core/enums/evu.py
dgpy/core/enums/exe_enums.py
dgpy/core/enums/prefix.py
dgpy/core/exe.py
dgpy/core/header.py
dgpy/core/py2grd.py
dgpy/core/py3grd.py
dgpy/core/py6grd/__init__.py
dgpy/core/py6grd/evg.py
dgpy/core/py6grd/magic.py
dgpy/core/py6grd/py6grd_base.py
dgpy/core/py6grd/py6grd_dto.py
dgpy/core/py6grd/py6grd_io.py
dgpy/core/pyspace.py
dgpy/core/validators.py
dgpy/cv.py
dgpy/cv.pyi
dgpy/datfield.py
dgpy/decorate.py
dgpy/dev/__init__.py
dgpy/dev/_dgpy_module_template.py
dgpy/dgdal.py
dgpy/dgi_coordinate_systems.py
dgpy/dgidump.py
dgpy/dgimage.py
dgpy/dgio.py
dgpy/dgipython.py
dgpy/dgnumpy.py
dgpy/dgpydantic.py
dgpy/enums.py
dgpy/ev.py
dgpy/ev.pyi
dgpy/ex.py
dgpy/fmts.py
dgpy/geojson.py
dgpy/h5.py
dgpy/hypothesis.py
dgpy/insp.py
dgpy/json.py
dgpy/libimageio.py
dgpy/libmultigrid/__init__.py
dgpy/libmultigrid/_utils.py
dgpy/libmultigrid/attributes.py
dgpy/libmultigrid/axis_label.py
dgpy/libmultigrid/enums.py
dgpy/libmultigrid/h5_models.py
dgpy/libpd.py
dgpy/librich.py
dgpy/librio.py
dgpy/libxr.py
dgpy/listless.py
dgpy/maths.py
dgpy/npt.py
dgpy/parsing.py
dgpy/process.py
dgpy/py.typed
dgpy/pyc3grd.py
dgpy/pydat.py
dgpy/pygrd.py
dgpy/pyviewserver/__init__.py
dgpy/pyviewserver/_const.py
dgpy/pyviewserver/_types.py
dgpy/sh.py
dgpy/status.py
dgpy/testing/__init__.py
dgpy/testing/cmp.py
dgpy/testing/diff.py
dgpy/testing/pref.py
dgpy/testing/pref.pyi
dgpy/testing/profiling.py
dgpy/testing/pydat.py
dgpy/utils/__init__.py
dgpy/utils/builtins.py
dgpy/utils/hash.py
dgpy/utils/web.py
dgpy/wa.py
dgpy/wa.pyi
dgpy/xtypes.py
dgpy/ykk.py
dgpy-0.10.4.dist-info/licenses/LICENSE
dgpy-0.10.4.dist-info/WHEEL
dgpy-0.10.4.dist-info/METADATA
dgpy-0.10.4.dist-info/RECORD
