Metadata-Version: 2.4
Name: dgpy
Version: 0.10.4
Summary: Dynamic Graphics Python
Keywords: dgi,dgpy,dgpylibs,python3,typed
Author: jesse, dan
Author-email: jesse <jesse@dgi.com>, dan <dan@dgi.com>
License-File: LICENSE
Classifier: Development Status :: 5 - Production/Stable
Classifier: Intended Audience :: Developers
Classifier: License :: Other/Proprietary License
Classifier: Programming Language :: Python
Classifier: Programming Language :: Python :: 3 :: Only
Classifier: Programming Language :: Python :: 3.11
Classifier: Programming Language :: Python :: 3.12
Classifier: Programming Language :: Python :: 3.13
Classifier: Typing :: Typed
Requires-Dist: aiopen>=0.8.0
Requires-Dist: asyncify>=0.12.0
Requires-Dist: fmts>=0.4.0
Requires-Dist: h5>=0.12.0
Requires-Dist: jsonbourne>=0.32.0
Requires-Dist: listless>=0.4.0
Requires-Dist: numpy>=1.23
Requires-Dist: pandas>=1.5.0
Requires-Dist: pydantic>=2.8.2
Requires-Dist: pyzmq>=26.2,<27
Requires-Dist: requires>=0.12.0
Requires-Dist: shellfish>=0.7.0
Requires-Dist: typing-extensions>=4.14.1
Requires-Dist: xarray>=2023.12
Requires-Dist: imageio>=2.35.1 ; extra == 'all'
Requires-Dist: imageio>=2.35.1 ; extra == 'full'
Requires-Python: >=3.11
Provides-Extra: all
Provides-Extra: full
